census_request_api/__init__.py
census_request_api/main.py
census_request_api-0.0.2.dist-info/METADATA
census_request_api-0.0.2.dist-info/WHEEL
census_request_api-0.0.2.dist-info/top_level.txt
census_request_api-0.0.2.dist-info/RECORD
