Metadata-Version: 2.1
Name: census_request_api
Version: 0.0.2
Author: lennon0926
Author-email: <onnelle.lugo@upr.edu>
Requires-Dist: requests
Requires-Dist: pandas
